my_instagram_lib/__init__.py
hnt-0.1.dist-info/METADATA
hnt-0.1.dist-info/WHEEL
hnt-0.1.dist-info/top_level.txt
hnt-0.1.dist-info/RECORD
