Metadata-Version: 2.1
Name: hnt
Version: 0.1
Summary: Thư viện lấy thông tin Instagram cơ bản
Author: X
Author-email: truong77kk@gmail.com
Classifier: Programming Language :: Python :: 3
Classifier: License :: OSI Approved :: MIT License
Requires-Dist: instaloader
